{
  "page": "partner-program",
  "savedAt": "2026-02-21T05:01:25.110Z",
  "sections": {
    "fullpage": {
      "diffPercent": 6.88,
      "verdict": "FAIL",
      "skipped": false
    },
    "hero": {
      "diffPercent": 0.78,
      "verdict": "MATCH",
      "skipped": false
    },
    "pain-revenue": {
      "diffPercent": 0.28,
      "verdict": "MATCH",
      "skipped": false
    },
    "pain-operational": {
      "diffPercent": 0.51,
      "verdict": "MATCH",
      "skipped": false
    },
    "alternative": {
      "diffPercent": 2.73,
      "verdict": "REVIEW",
      "skipped": false
    },
    "offerings": {
      "diffPercent": 0.69,
      "verdict": "MATCH",
      "skipped": false
    },
    "journey-research": {
      "diffPercent": 3.67,
      "verdict": "REVIEW",
      "skipped": false
    },
    "journey-tiers": {
      "diffPercent": 1.91,
      "verdict": "MATCH",
      "skipped": false
    },
    "market-timing": {
      "diffPercent": 3.75,
      "verdict": "REVIEW",
      "skipped": false
    },
    "final-cta": {
      "diffPercent": 4.79,
      "verdict": "REVIEW",
      "skipped": false
    }
  }
}