{
  "data": "[et_pb_section fb_built=\"1\" _builder_version=\"4.27.0\" background_color=\"#f8fafc\" custom_padding=\"60px||60px||true|false\" global_colors_info=\"{}\"]\n[et_pb_row _builder_version=\"4.27.0\" max_width=\"1200px\" custom_padding=\"0px||0px||false|false\" global_colors_info=\"{}\"]\n[et_pb_column type=\"4_4\" _builder_version=\"4.27.0\" global_colors_info=\"{}\"]\n[et_pb_text _builder_version=\"4.27.0\" text_font=\"JetBrains Mono|500|||||||\" text_text_color=\"#64748b\" text_font_size=\"12px\" text_letter_spacing=\"2px\" text_orientation=\"center\" custom_margin=\"||40px||false|false\" global_colors_info=\"{}\"]\n<p style=\"text-transform: uppercase;\">Trusted by Leading Manufacturers in Thailand</p>\n[/et_pb_text]\n[/et_pb_column]\n[/et_pb_row]\n[et_pb_row column_structure=\"1_6,1_6,1_6,1_6,1_6,1_6\" _builder_version=\"4.27.0\" max_width=\"1200px\" custom_padding=\"0px||48px||false|false\" global_colors_info=\"{}\"]\n[et_pb_column type=\"1_6\" _builder_version=\"4.27.0\" global_colors_info=\"{}\"]\n[et_pb_image src=\"/logos/client-1.png\" alt=\"Client Logo 1\" align=\"center\" _builder_version=\"4.27.0\" max_height=\"48px\" filter_saturate=\"0%\" filter_opacity=\"60%\" filter_saturate__hover_enabled=\"on|hover\" filter_saturate__hover=\"100%\" filter_opacity__hover_enabled=\"on|hover\" filter_opacity__hover=\"100%\" global_colors_info=\"{}\"]\n[/et_pb_image]\n[/et_pb_column]\n[et_pb_column type=\"1_6\" _builder_version=\"4.27.0\" global_colors_info=\"{}\"]\n[et_pb_image src=\"/logos/client-2.png\" alt=\"Client Logo 2\" align=\"center\" _builder_version=\"4.27.0\" max_height=\"48px\" filter_saturate=\"0%\" filter_opacity=\"60%\" filter_saturate__hover_enabled=\"on|hover\" filter_saturate__hover=\"100%\" filter_opacity__hover_enabled=\"on|hover\" filter_opacity__hover=\"100%\" global_colors_info=\"{}\"]\n[/et_pb_image]\n[/et_pb_column]\n[et_pb_column type=\"1_6\" _builder_version=\"4.27.0\" global_colors_info=\"{}\"]\n[et_pb_image src=\"/logos/client-3.png\" alt=\"Client Logo 3\" align=\"center\" _builder_version=\"4.27.0\" max_height=\"48px\" filter_saturate=\"0%\" filter_opacity=\"60%\" filter_saturate__hover_enabled=\"on|hover\" filter_saturate__hover=\"100%\" filter_opacity__hover_enabled=\"on|hover\" filter_opacity__hover=\"100%\" global_colors_info=\"{}\"]\n[/et_pb_image]\n[/et_pb_column]\n[et_pb_column type=\"1_6\" _builder_version=\"4.27.0\" global_colors_info=\"{}\"]\n[et_pb_image src=\"/logos/client-4.png\" alt=\"Client Logo 4\" align=\"center\" _builder_version=\"4.27.0\" max_height=\"48px\" filter_saturate=\"0%\" filter_opacity=\"60%\" filter_saturate__hover_enabled=\"on|hover\" filter_saturate__hover=\"100%\" filter_opacity__hover_enabled=\"on|hover\" filter_opacity__hover=\"100%\" global_colors_info=\"{}\"]\n[/et_pb_image]\n[/et_pb_column]\n[et_pb_column type=\"1_6\" _builder_version=\"4.27.0\" global_colors_info=\"{}\"]\n[et_pb_image src=\"/logos/client-5.png\" alt=\"Client Logo 5\" align=\"center\" _builder_version=\"4.27.0\" max_height=\"48px\" filter_saturate=\"0%\" filter_opacity=\"60%\" filter_saturate__hover_enabled=\"on|hover\" filter_saturate__hover=\"100%\" filter_opacity__hover_enabled=\"on|hover\" filter_opacity__hover=\"100%\" global_colors_info=\"{}\"]\n[/et_pb_image]\n[/et_pb_column]\n[et_pb_column type=\"1_6\" _builder_version=\"4.27.0\" global_colors_info=\"{}\"]\n[et_pb_image src=\"/logos/client-6.png\" alt=\"Client Logo 6\" align=\"center\" _builder_version=\"4.27.0\" max_height=\"48px\" filter_saturate=\"0%\" filter_opacity=\"60%\" filter_saturate__hover_enabled=\"on|hover\" filter_saturate__hover=\"100%\" filter_opacity__hover_enabled=\"on|hover\" filter_opacity__hover=\"100%\" global_colors_info=\"{}\"]\n[/et_pb_image]\n[/et_pb_column]\n[/et_pb_row]\n[et_pb_row column_structure=\"1_3,1_3,1_3\" _builder_version=\"4.27.0\" max_width=\"1200px\" border_width_top=\"1px\" border_color_top=\"#e2e8f0\" custom_padding=\"32px||0px||false|false\" global_colors_info=\"{}\"]\n[et_pb_column type=\"1_3\" _builder_version=\"4.27.0\" global_colors_info=\"{}\"]\n[et_pb_number_counter title=\"Factories Worldwide\" number=\"50000\" percent_sign=\"off\" _builder_version=\"4.27.0\" title_font=\"Source Sans 3||||||||\" title_text_color=\"#64748b\" title_font_size=\"13px\" number_font=\"Lexend|700|||||||\" number_text_color=\"#253B50\" number_font_size=\"28px\" text_orientation=\"center\" global_colors_info=\"{}\"]\n[/et_pb_number_counter]\n[/et_pb_column]\n[et_pb_column type=\"1_3\" _builder_version=\"4.27.0\" global_colors_info=\"{}\"]\n[et_pb_number_counter title=\"Years in Manufacturing\" number=\"44\" percent_sign=\"off\" _builder_version=\"4.27.0\" title_font=\"Source Sans 3||||||||\" title_text_color=\"#64748b\" title_font_size=\"13px\" number_font=\"Lexend|700|||||||\" number_text_color=\"#253B50\" number_font_size=\"28px\" text_orientation=\"center\" global_colors_info=\"{}\"]\n[/et_pb_number_counter]\n[/et_pb_column]\n[et_pb_column type=\"1_3\" _builder_version=\"4.27.0\" global_colors_info=\"{}\"]\n[et_pb_text _builder_version=\"4.27.0\" text_font=\"Source Sans 3||||||||\" text_text_color=\"#64748b\" text_font_size=\"13px\" text_orientation=\"center\" global_colors_info=\"{}\"]\n<p style=\"font-family: 'Lexend', sans-serif; font-size: 28px; font-weight: 700; color: #253B50; margin-bottom: 4px;\">Certified</p>\n<p>Thai Revenue Department</p>\n[/et_pb_text]\n[/et_pb_column]\n[/et_pb_row]\n[/et_pb_section]",
  "context": "et_builder_layouts",
  "info": {
    "name": "DigiWin Homepage - Section 2: Client Logos",
    "description": "Client logo bar with 6 placeholder logos (grayscale, color on hover) plus 3 trust stats below: 50,000+ Factories, 44 Years, Thai RD Certified.",
    "divi_modules_used": [
      "et_pb_section (light gray background)",
      "et_pb_row (1/6 x6 for logos, 1/3 x3 for stats)",
      "et_pb_text (section label)",
      "et_pb_image (6 client logos with grayscale filter)",
      "et_pb_number_counter (factory count, years)",
      "et_pb_text (certified stat - text, not counter)"
    ],
    "colors": {
      "section_bg": "#f8fafc",
      "label_text": "#64748b",
      "stat_value": "#253B50",
      "border": "#e2e8f0"
    },
    "notes": [
      "Replace /logos/client-N.png with actual client logos after import",
      "Logo images use filter_saturate=0% + filter_opacity=60% for grayscale effect",
      "Hover enables full color (saturate 100%, opacity 100%)",
      "Stats row has top border to separate from logos"
    ]
  }
}
